setup.py
crazydistributions/Binomialdistribution.py
crazydistributions/Gaussiandistribution.py
crazydistributions/Generaldistribution.py
crazydistributions/__init__.py
crazydistributions.egg-info/PKG-INFO
crazydistributions.egg-info/SOURCES.txt
crazydistributions.egg-info/dependency_links.txt
crazydistributions.egg-info/not-zip-safe
crazydistributions.egg-info/top_level.txt